nlb/arduino/client.py
nlb/authentik/client.py
nlb/authentik/nlb_invite
nlb/authentik/nlb_invite.py
nlb/authentik/nlb_invite.venv.pth
nlb/buffham/bh.py
nlb/buffham/buffham
nlb/buffham/buffham.py
nlb/buffham/buffham.venv.pth
nlb/buffham/cpp_generator.py
nlb/buffham/engine.py
nlb/buffham/parser.py
nlb/buffham/py_generator.py
nlb/buffham/template_generator.py
nlb/datastructure/bidirectional_dict.py
nlb/github/nlb_gh_feature
nlb/github/nlb_gh_feature.py
nlb/github/nlb_gh_feature.venv.pth
nlb/hyd/progress_bar.py
nlb/mcp/arduino.py
nlb/mcp/arduino_mcp
nlb/mcp/arduino_mcp.py
nlb/mcp/arduino_mcp.venv.pth
nlb/mcp/file_edit.py
nlb/mcp/file_edit_mcp
nlb/mcp/file_edit_mcp.py
nlb/mcp/file_edit_mcp.venv.pth
nlb/mcp/tool_manager.py
nlb/mcp/util.py
nlb/sharetrace/interface.py
nlb/sharetrace/sharetrace
nlb/sharetrace/sharetrace.py
nlb/sharetrace/sharetrace.venv.pth
nlb/sharetrace/sharetrace_demo
nlb/sharetrace/sharetrace_demo.py
nlb/sharetrace/sharetrace_demo.venv.pth
nlb/sharetrace/st.py
nlb/tailscale/nlb_tailscale
nlb/tailscale/nlb_tailscale.py
nlb/tailscale/nlb_tailscale.venv.pth
nlb/util/click_utils.py
nlb/util/console_utils.py
nlb/util/dataclass.py
nlb/util/exception.py
nlb/util/introspection.py
nlb/util/path_utils.py
nlb/util/prompt_utils.py
nlb/util/secrets.py
nlb/util/semantic_errors.py
nlb/util/venv_completions
nlb/util/venv_completions.py
nlb/util/venv_completions.venv.pth
nlb/util/version.py
nlb/wizaidry/audio_util.py
nlb/wizaidry/text_handler.py
nlb/wizaidry/util.py
nlb/wizaidry/voice_handler.py
nl_blocks-0.7.1.dist-info/WHEEL
nl_blocks-0.7.1.dist-info/METADATA
nl_blocks-0.7.1.dist-info/entry_points.txt
nl_blocks-0.7.1.data/data/share/completions/arduino_mcp-completion.bash
nl_blocks-0.7.1.data/data/share/completions/buffham-completion.bash
nl_blocks-0.7.1.data/data/share/completions/file_edit_mcp-completion.bash
nl_blocks-0.7.1.data/data/share/completions/nlb_gh_feature-completion.bash
nl_blocks-0.7.1.data/data/share/completions/nlb_invite-completion.bash
nl_blocks-0.7.1.data/data/share/completions/nlb_tailscale-completion.bash
nl_blocks-0.7.1.dist-info/RECORD
